autowoe/__init__.py
autowoe/lib/__init__.py
autowoe/lib/autowoe.py
autowoe/lib/cat_encoding/__init__.py
autowoe/lib/cat_encoding/cat_encoding.py
autowoe/lib/logging.py
autowoe/lib/optimizer/__init__.py
autowoe/lib/optimizer/optimizer.py
autowoe/lib/pipelines/__init__.py
autowoe/lib/pipelines/pipeline_feature_special_values.py
autowoe/lib/pipelines/pipeline_homotopy.py
autowoe/lib/report/__init__.py
autowoe/lib/report/autowoe_report_template.html
autowoe/lib/report/report.py
autowoe/lib/report/report_en_v2.html
autowoe/lib/report/report_generator.py
autowoe/lib/report/shaptxt
autowoe/lib/report/utilities_images/__init__.py
autowoe/lib/report/utilities_images/utilities_images.py
autowoe/lib/selectors/__init__.py
autowoe/lib/selectors/composed_selector.py
autowoe/lib/selectors/l1.py
autowoe/lib/selectors/selector_first.py
autowoe/lib/selectors/selector_last.py
autowoe/lib/selectors/utils.py
autowoe/lib/types_handler/__init__.py
autowoe/lib/types_handler/features_checkers_handlers.py
autowoe/lib/types_handler/types_handler.py
autowoe/lib/utilities/__init__.py
autowoe/lib/utilities/cv_split_f.py
autowoe/lib/utilities/eli5_permutation.py
autowoe/lib/utilities/refit.py
autowoe/lib/utilities/s3.py
autowoe/lib/utilities/sql.py
autowoe/lib/utilities/utils.py
autowoe/lib/woe/__init__.py
autowoe/lib/woe/woe.py
autowoe-1.4.0.dist-info/LICENSE
autowoe-1.4.0.dist-info/METADATA
autowoe-1.4.0.dist-info/WHEEL
autowoe-1.4.0.dist-info/RECORD
