Metadata-Version: 2.1
Name: AutoWoE
Version: 1.4.0
Summary: Library for automatic interpretable model building (Whitebox AutoML)
Home-page: https://github.com/AILab-MLTools/AutoMLWhitebox
Author: Vakhrushev Anton
Author-email: btbpanda@gmail.com
Requires-Python: >=3.8
Classifier: Development Status :: 3 - Alpha
Classifier: Environment :: Console
Classifier: Intended Audience :: Science/Research
Classifier: Natural Language :: English
Classifier: Operating System :: OS Independent
Classifier: Programming Language :: Python :: 3
Classifier: Programming Language :: Python :: 3.8
Classifier: Programming Language :: Python :: 3.9
Classifier: Programming Language :: Python :: 3.10
Classifier: Programming Language :: Python :: 3.11
Classifier: Programming Language :: Python :: 3.12
Classifier: Programming Language :: Python :: 3.13
Classifier: Topic :: Scientific/Engineering :: Artificial Intelligence
Classifier: Typing :: Typed
Requires-Dist: StrEnum (>=0.4.7,<0.5.0)
Requires-Dist: jinja2
Requires-Dist: joblib
Requires-Dist: lightgbm
Requires-Dist: matplotlib
Requires-Dist: numpy
Requires-Dist: pandas
Requires-Dist: pytest
Requires-Dist: pytz
Requires-Dist: scikit-learn
Requires-Dist: scipy
Requires-Dist: seaborn
Requires-Dist: sphinx
Requires-Dist: sphinx-rtd-theme
Requires-Dist: tqdm (>=4.62.3,<5.0.0)
Project-URL: Repository, https://github.com/AILab-MLTools/AutoMLWhitebox
